pinry_cli.py
pinry_cli-0.1.0.dist-info/entry_points.txt
pinry_cli-0.1.0.dist-info/LICENSE
pinry_cli-0.1.0.dist-info/WHEEL
pinry_cli-0.1.0.dist-info/METADATA
pinry_cli-0.1.0.dist-info/RECORD
