Metadata-Version: 2.1
Name: pinry-cli
Version: 0.1.0
Summary: Pinry CLI to upload local image to remote Pinry instance
License: MIT
Author: winkidney
Author-email: winkidney@gmail.com
Requires-Python: >=3.6,<4.0
Classifier: License :: OSI Approved :: MIT License
Classifier: Programming Language :: Python :: 3
Classifier: Programming Language :: Python :: 3.10
Classifier: Programming Language :: Python :: 3.6
Classifier: Programming Language :: Python :: 3.7
Classifier: Programming Language :: Python :: 3.8
Classifier: Programming Language :: Python :: 3.9
Requires-Dist: click (>=8.0.4,<9.0.0)
Requires-Dist: requests (>=2.27.1,<3.0.0)
